faceie/__init__.py
faceie/image_to_array.py
faceie/nn.py
faceie/nn_arguments.py
faceie/py.typed
faceie/facenet/__init__.py
faceie/facenet/model.py
faceie/mtcnn/__init__.py
faceie/mtcnn/detect_faces.py
faceie/mtcnn/model.py
faceie/mtcnn/non_maximum_suppression.py
faceie/mtcnn/pyramid.py
faceie/mtcnn/data/README.md
faceie/mtcnn/data/o_net_weights.pickle
faceie/mtcnn/data/p_net_weights.pickle
faceie/mtcnn/data/r_net_weights.pickle
faceie/scripts/__init__.py
faceie/scripts/convert_facenet_weights.py
faceie/scripts/convert_mtcnn_weights.py
faceie-0.0.5.dist-info/LICENSE
faceie-0.0.5.dist-info/METADATA
faceie-0.0.5.dist-info/WHEEL
faceie-0.0.5.dist-info/entry_points.txt
faceie-0.0.5.dist-info/top_level.txt
faceie-0.0.5.dist-info/RECORD
