Metadata-Version: 2.2
Name: faceie
Version: 0.0.5
Summary: An pure Numpy implementation of MTCNN face detection and an Inception-ResNet-v1 based FaceNet-style face encoder.
License:                     GNU GENERAL PUBLIC LICENSE
Project-URL: source, https://github.com/mossblaser/faceie
License-File: LICENSE
Requires-Dist: numpy
Requires-Dist: pillow
Requires-Dist: weightie<1.0.0,>=0.0.1
Provides-Extra: convert
Requires-Dist: torch; extra == "convert"
Requires-Dist: torchvision; extra == "convert"
